mscript/__init__.py
mscript-1.0.1.dist-info/DESCRIPTION.rst
mscript-1.0.1.dist-info/entry_points.txt
mscript-1.0.1.dist-info/METADATA
mscript-1.0.1.dist-info/metadata.json
mscript-1.0.1.dist-info/RECORD
mscript-1.0.1.dist-info/top_level.txt
mscript-1.0.1.dist-info/WHEEL
